databridge/__init__.py
databridge/databridge.py
tests/__init__.py
tests/run.py
tests/test_config_updater.py
databridge-0.2.6.dist-info/LICENSE
databridge-0.2.6.dist-info/METADATA
databridge-0.2.6.dist-info/WHEEL
databridge-0.2.6.dist-info/top_level.txt
databridge-0.2.6.dist-info/RECORD
