Metadata-Version: 2.1
Name: databridge
Version: 0.2.6
Summary: Bridge shared datasets across diverse projects.
Author: Rodolfo Souza
Author-email: souzarod@proton.me
License: MIT
Classifier: License :: OSI Approved :: MIT License
Classifier: Programming Language :: Python :: 3.10
Classifier: Operating System :: OS Independent
Requires-Python: >=3.10
License-File: LICENSE
Requires-Dist: pandas
Requires-Dist: geopandas
Requires-Dist: polars
Requires-Dist: prettytable
Provides-Extra: dev
Requires-Dist: pytest ; extra == 'dev'
Requires-Dist: twine ; extra == 'dev'
